{
  "actions": [
    { "type": "AddEndpoint", "x": 10, "y": 0 },
    { "type": "AddEndpoint", "x": 3, "y": 4 },
    
    { "type": "AddEndpoint", "x": 10, "y": 4 },
    { "type": "AddEndpoint", "x": 1, "y": 7 },
    
    { "type": "AddEndpoint", "x": 2, "y": 14 },
    { "type": "AddEndpoint", "x": 7, "y": 6 },
    
    { "type": "AddEndpoint", "x": 1, "y": 13 },
    { "type": "AddEndpoint", "x": 8, "y": 6 },
    
    { "type": "AddEndpoint", "x": 1, "y": 4 },
    { "type": "AddEndpoint", "x": 9, "y": 0 },
    
    { "type": "AddEndpoint", "x": 10, "y": 3 },
    { "type": "AddEndpoint", "x": 6, "y": 11 },
    
    { "type": "AddEndpoint", "x": 11, "y": 6 },
    { "type": "AddEndpoint", "x": 3, "y": 12 },
    
    { "type": "AddEndpoint", "x": 11, "y": 0 },
    { "type": "AddEndpoint", "x": 11, "y": 13 },
    
    { "type": "AddEndpoint", "x": 2, "y": 2 },
    { "type": "AddEndpoint", "x": 8, "y": 0 }
  ]
}
